ProgrammingLanguagesApplicationAndInterpretationZhongwenban/README.md
ProgrammingLanguagesApplicationAndInterpretationZhongwenban/__init__.py
ProgrammingLanguagesApplicationAndInterpretationZhongwenban/__main__.py
ProgrammingLanguagesApplicationAndInterpretationZhongwenban/file.epub
ProgrammingLanguagesApplicationAndInterpretationZhongwenban/index.html
ProgrammingLanguagesApplicationAndInterpretationZhongwenban/css/__init__.py
ProgrammingLanguagesApplicationAndInterpretationZhongwenban/css/annotations.css
ProgrammingLanguagesApplicationAndInterpretationZhongwenban/css/main.css
ProgrammingLanguagesApplicationAndInterpretationZhongwenban/css/normalize.css
ProgrammingLanguagesApplicationAndInterpretationZhongwenban/css/popup.css
ProgrammingLanguagesApplicationAndInterpretationZhongwenban/font/__init__.py
ProgrammingLanguagesApplicationAndInterpretationZhongwenban/font/fontello.eot
ProgrammingLanguagesApplicationAndInterpretationZhongwenban/font/fontello.svg
ProgrammingLanguagesApplicationAndInterpretationZhongwenban/font/fontello.ttf
ProgrammingLanguagesApplicationAndInterpretationZhongwenban/font/fontello.woff
ProgrammingLanguagesApplicationAndInterpretationZhongwenban/img/__init__.py
ProgrammingLanguagesApplicationAndInterpretationZhongwenban/img/annotator-glyph-sprite.png
ProgrammingLanguagesApplicationAndInterpretationZhongwenban/img/annotator-icon-sprite.png
ProgrammingLanguagesApplicationAndInterpretationZhongwenban/img/apple-touch-icon.png
ProgrammingLanguagesApplicationAndInterpretationZhongwenban/img/cancelfullscreen.png
ProgrammingLanguagesApplicationAndInterpretationZhongwenban/img/close.png
ProgrammingLanguagesApplicationAndInterpretationZhongwenban/img/fullscreen.png
ProgrammingLanguagesApplicationAndInterpretationZhongwenban/img/loader.gif
ProgrammingLanguagesApplicationAndInterpretationZhongwenban/img/menu-icon.png
ProgrammingLanguagesApplicationAndInterpretationZhongwenban/img/save.png
programming_languages_application_and_interpretation_zhongwenban-2024.3.3.0.dist-info/METADATA
programming_languages_application_and_interpretation_zhongwenban-2024.3.3.0.dist-info/WHEEL
programming_languages_application_and_interpretation_zhongwenban-2024.3.3.0.dist-info/entry_points.txt
programming_languages_application_and_interpretation_zhongwenban-2024.3.3.0.dist-info/top_level.txt
programming_languages_application_and_interpretation_zhongwenban-2024.3.3.0.dist-info/RECORD
